clee
