Metadata-Version: 1.0
Name: clee
Version: 0.3
Summary: Quick Command Line Interfaces
Home-page: http://an9.org/w/CleePy
Author: Andy Smith
Author-email: clee_py@anarkystic.com
License: MIT License
Platform: UNKNOWN
Classifier: Development Status :: 4 - Beta
Classifier: Intended Audience :: Developers
Classifier: License :: OSI Approved :: MIT License
Classifier: Natural Language :: English
Classifier: Operating System :: OS Independent
Classifier: Programming Language :: Python
Classifier: Topic :: Software Development
